odoo/addons/stock_move_manual_lot/README.rst
odoo/addons/stock_move_manual_lot/__init__.py
odoo/addons/stock_move_manual_lot/__manifest__.py
odoo/addons/stock_move_manual_lot/hooks.py
odoo/addons/stock_move_manual_lot/i18n/stock_move_manual_lot.pot
odoo/addons/stock_move_manual_lot/migrations/12.0.1.1.0/post-migration.py
odoo/addons/stock_move_manual_lot/models/__init__.py
odoo/addons/stock_move_manual_lot/models/stock_move.py
odoo/addons/stock_move_manual_lot/models/stock_move_line.py
odoo/addons/stock_move_manual_lot/models/stock_picking.py
odoo/addons/stock_move_manual_lot/models/stock_picking_type.py
odoo/addons/stock_move_manual_lot/readme/CONTRIBUTORS.rst
odoo/addons/stock_move_manual_lot/readme/DESCRIPTION.rst
odoo/addons/stock_move_manual_lot/readme/USAGE.rst
odoo/addons/stock_move_manual_lot/readme/newsfragments/.gitkeep
odoo/addons/stock_move_manual_lot/static/description/icon.png
odoo/addons/stock_move_manual_lot/static/description/index.html
odoo/addons/stock_move_manual_lot/tests/__init__.py
odoo/addons/stock_move_manual_lot/tests/test_stock_move_manual_lot.py
odoo/addons/stock_move_manual_lot/views/stock_move_line.xml
odoo/addons/stock_move_manual_lot/views/stock_picking.xml
odoo/addons/stock_move_manual_lot/views/stock_picking_type.xml
odoo12_addon_stock_move_manual_lot-12.0.1.1.0.99.dev8.dist-info/METADATA
odoo12_addon_stock_move_manual_lot-12.0.1.1.0.99.dev8.dist-info/WHEEL
odoo12_addon_stock_move_manual_lot-12.0.1.1.0.99.dev8.dist-info/top_level.txt
odoo12_addon_stock_move_manual_lot-12.0.1.1.0.99.dev8.dist-info/RECORD
