Metadata-Version: 2.1
Name: odoo12-addon-stock-move-manual-lot
Version: 12.0.1.1.0.99.dev8
Summary: Force the user to manually select a lot
Home-page: https://github.com/OCA/stock-logistics-workflow
Author: Hunki Enterprises BV,Opener B.V.,Odoo Community Association (OCA)
Author-email: support@odoo-community.org
License: AGPL-3
Platform: UNKNOWN
Classifier: Programming Language :: Python
Classifier: Framework :: Odoo
Classifier: Framework :: Odoo :: 12.0
Classifier: License :: OSI Approved :: GNU Affero General Public License v3
Requires-Python: >=3.5
Requires-Dist: odoo12-addon-base-view-inheritance-extension
Requires-Dist: odoo <12.1dev,>=12.0a
